setup.py
httpoutputstream/__init__.py
httpoutputstream/stream.py
httpoutputstream.egg-info/PKG-INFO
httpoutputstream.egg-info/SOURCES.txt
httpoutputstream.egg-info/dependency_links.txt
httpoutputstream.egg-info/top_level.txt