Metadata-Version: 1.1
Name: httpoutputstream
Version: 1.0.0
Summary: httplib stream wrapper for response to use send as an output stream
Home-page: https://github.com/salimm/httpoutpustream
Author: Salim Malakouti
Author-email: salim.malakouti@gmail.com
License: MIT
Download-URL: https://github.com/salimm/httpoutpustream/archive/1.0.0.tar.gz
Keywords: streaming,http,client
Platform: UNKNOWN
Classifier: Programming Language :: Python
